env_doctor/__init__.py
env_doctor/checks.py
env_doctor/cli.py
env_doctor/db.py
env_doctor/core/__init__.py
env_doctor/core/detector.py
env_doctor/core/exceptions.py
env_doctor/core/registry.py
env_doctor/data/compatibility.json
env_doctor/data/migrations.json
env_doctor/data/model_requirements.json
env_doctor/detectors/__init__.py
env_doctor/detectors/cuda_toolkit.py
env_doctor/detectors/cudnn.py
env_doctor/detectors/nvidia_driver.py
env_doctor/detectors/python_libraries.py
env_doctor/detectors/wsl2.py
env_doctor/utilities/__init__.py
env_doctor/utilities/model_checker.py
env_doctor/utilities/vram_calculator.py
env_doctor/validators/__init__.py
env_doctor/validators/compat_db.py
env_doctor/validators/compose_validator.py
env_doctor/validators/dockerfile_validator.py
env_doctor/validators/models.py
env_doctor-0.1.0.dist-info/licenses/LICENSE
env_doctor-0.1.0.dist-info/METADATA
env_doctor-0.1.0.dist-info/WHEEL
env_doctor-0.1.0.dist-info/entry_points.txt
env_doctor-0.1.0.dist-info/top_level.txt
env_doctor-0.1.0.dist-info/RECORD
