Metadata-Version: 2.4
Name: env-doctor
Version: 0.1.0
Summary: A CLI tool to verify and fix AI/ML environment compatibility (Driver <-> CUDA <-> Wheels).
Author-email: Mitul Garg <mitulgarg3@gmail.com>, Tharun Anand <atharun05@gmail.com>
License: MIT License
Project-URL: Homepage, https://github.com/mitulgarg/env-doctor
Project-URL: Bug Tracker, https://github.com/mitulgarg/env-doctor/issues
Classifier: Programming Language :: Python :: 3
Classifier: License :: OSI Approved :: MIT License
Classifier: Operating System :: POSIX :: Linux
Classifier: Operating System :: Microsoft :: Windows
Classifier: Topic :: Scientific/Engineering :: Artificial Intelligence
Classifier: Topic :: System :: Hardware
Requires-Python: >=3.7
License-File: LICENSE
Requires-Dist: nvidia-ml-py
Requires-Dist: packaging
Requires-Dist: click
Requires-Dist: requests
Requires-Dist: pyyaml
Dynamic: license-file
